ncipysidekick/__init__.py
ncipysidekick/example.py
ncipysidekick-0.0.1.dist-info/METADATA
ncipysidekick-0.0.1.dist-info/WHEEL
ncipysidekick-0.0.1.dist-info/top_level.txt
ncipysidekick-0.0.1.dist-info/RECORD
